jira_mcp/__init__.py
jira_mcp/__main__.py
jira_mcp/config.py
jira_mcp/server.py
jira_mcp/scripts/__init__.py
jira_mcp/scripts/download_all_attachments.py
jira_mcp/scripts/extract_attachment.py
personal_jira_mcp-0.1.0.dist-info/METADATA
personal_jira_mcp-0.1.0.dist-info/WHEEL
personal_jira_mcp-0.1.0.dist-info/entry_points.txt
personal_jira_mcp-0.1.0.dist-info/licenses/LICENSE
personal_jira_mcp-0.1.0.dist-info/RECORD
